odoo8_addon_account_bank_statement_import_mt940_base-8.0.1.1.1-py2.7-nspkg.pth
odoo8_addon_account_bank_statement_import_mt940_base-8.0.1.1.1.dist-info/top_level.txt
odoo8_addon_account_bank_statement_import_mt940_base-8.0.1.1.1.dist-info/WHEEL
odoo8_addon_account_bank_statement_import_mt940_base-8.0.1.1.1.dist-info/RECORD
odoo8_addon_account_bank_statement_import_mt940_base-8.0.1.1.1.dist-info/metadata.json
odoo8_addon_account_bank_statement_import_mt940_base-8.0.1.1.1.dist-info/DESCRIPTION.rst
odoo8_addon_account_bank_statement_import_mt940_base-8.0.1.1.1.dist-info/METADATA
odoo8_addon_account_bank_statement_import_mt940_base-8.0.1.1.1.dist-info/namespace_packages.txt
odoo_addons/account_bank_statement_import_mt940_base/__openerp__.py
odoo_addons/account_bank_statement_import_mt940_base/__init__.py
odoo_addons/account_bank_statement_import_mt940_base/README.rst
odoo_addons/account_bank_statement_import_mt940_base/mt940.py
