Metadata-Version: 2.0
Name: odoo8-addon-account-bank-statement-import-mt940-base
Version: 8.0.1.1.1
Summary: MT940 Bank Statements Import
Home-page: https://github.com/OCA/bank-statement-import
Author: UNKNOWN
Author-email: UNKNOWN
License: AGPL-3
Platform: UNKNOWN
Requires-Dist: odoo (<9.0a,>=8.0a)
Requires-Dist: odoo8-addon-account-bank-statement-import
Classifier: Programming Language :: Python :: 2.7
Classifier: Framework :: Odoo
Classifier: License :: OSI Approved :: GNU Affero General Public License v3
